satastro/__init__.py
satastro/satastro.py
satastro-1.0.4.dist-info/LICENSE
satastro-1.0.4.dist-info/METADATA
satastro-1.0.4.dist-info/WHEEL
satastro-1.0.4.dist-info/top_level.txt
satastro-1.0.4.dist-info/RECORD
