Metadata-Version: 2.1
Name: satastro
Version: 1.0.4
Summary: Mission analysis for astronomy mission with satellites
Author-email: Aurélien Genin <aurelien.genin@polytechnique.org>
Project-URL: Source, https://github.com/AstroAure/satastro
Classifier: Programming Language :: Python :: 3
Classifier: License :: OSI Approved :: GNU General Public License v3 (GPLv3)
Classifier: Operating System :: OS Independent
Requires-Python: >=3.9
License-File: LICENSE
Requires-Dist: tqdm
Requires-Dist: opencv-python
Requires-Dist: ffmpeg
Requires-Dist: numpy
Requires-Dist: pandas
Requires-Dist: matplotlib
Requires-Dist: astropy
Requires-Dist: poliastro
Requires-Dist: astroquery
Requires-Dist: cartopy
Requires-Dist: astral
